odoo/addons/l10n_ch_import_isr_v11/README.rst
odoo/addons/l10n_ch_import_isr_v11/__init__.py
odoo/addons/l10n_ch_import_isr_v11/__manifest__.py
odoo/addons/l10n_ch_import_isr_v11/static/description/icon.png
odoo/addons/l10n_ch_import_isr_v11/tests/__init__.py
odoo/addons/l10n_ch_import_isr_v11/tests/test_v11_import.py
odoo/addons/l10n_ch_import_isr_v11/tests/test_v11_files/test1.v11
odoo/addons/l10n_ch_import_isr_v11/wizard/__init__.py
odoo/addons/l10n_ch_import_isr_v11/wizard/isr_import.py
odoo/addons/l10n_ch_import_isr_v11/wizard/isr_import_view.xml
odoo11_addon_l10n_ch_import_isr_v11-11.0.1.0.0.dist-info/DESCRIPTION.rst
odoo11_addon_l10n_ch_import_isr_v11-11.0.1.0.0.dist-info/METADATA
odoo11_addon_l10n_ch_import_isr_v11-11.0.1.0.0.dist-info/RECORD
odoo11_addon_l10n_ch_import_isr_v11-11.0.1.0.0.dist-info/WHEEL
odoo11_addon_l10n_ch_import_isr_v11-11.0.1.0.0.dist-info/metadata.json
odoo11_addon_l10n_ch_import_isr_v11-11.0.1.0.0.dist-info/top_level.txt
